tno/fl/protocols/cox_regression/__init__.py
tno/fl/protocols/cox_regression/client.py
tno/fl/protocols/cox_regression/msg_ids.py
tno/fl/protocols/cox_regression/py.typed
tno/fl/protocols/cox_regression/schoenfeld_residuals.py
tno/fl/protocols/cox_regression/server.py
tno/fl/protocols/cox_regression/survival_stacking.py
tno/fl/protocols/cox_regression/tests/script_schoenfeld_residuals.py
tno/fl/protocols/cox_regression/tests/test_protocol.py
tno/fl/protocols/cox_regression/tests/test_schoenfeld_residuals.py
tno/fl/protocols/cox_regression/tests/test_stacking.py
tno/fl/protocols/cox_regression/tests/test_statistics.py
tno_fl_protocols_cox_regression-0.5.5.dist-info/LICENSE
tno_fl_protocols_cox_regression-0.5.5.dist-info/METADATA
tno_fl_protocols_cox_regression-0.5.5.dist-info/WHEEL
tno_fl_protocols_cox_regression-0.5.5.dist-info/top_level.txt
tno_fl_protocols_cox_regression-0.5.5.dist-info/RECORD
