Metadata-Version: 2.2
Name: tno.fl.protocols.cox_regression
Version: 0.5.5
Summary: Implementation of a Federated Learning scheme for Cox Regression
Author-email: TNO PET Lab <petlab@tno.nl>
Maintainer-email: TNO PET Lab <petlab@tno.nl>
License: Apache License, Version 2.0
Project-URL: Homepage, https://pet.tno.nl/
Project-URL: Documentation, https://docs.pet.tno.nl/fl/protocols/cox_regression/0.5.5
Project-URL: Source, https://github.com/TNO-FL/protocols.cox_regression
Keywords: TNO,FL,federated learning,machine learning,federated Cox regression
Platform: any
Classifier: License :: OSI Approved :: Apache Software License
Classifier: Programming Language :: Python :: 3
Classifier: Operating System :: OS Independent
Classifier: Intended Audience :: Developers
Classifier: Intended Audience :: Information Technology
Classifier: Intended Audience :: Science/Research
Classifier: Typing :: Typed
Requires-Python: >=3.9
License-File: LICENSE
Requires-Dist: numpy<3.0,>=1.17
Requires-Dist: typing_extensions>=4.7.1; python_version < "3.12"
Requires-Dist: tno.fl.protocols.logistic_regression~=1.1.0
Provides-Extra: schoenfeld-residuals
Requires-Dist: mpyc>=0.8; extra == "schoenfeld-residuals"
Requires-Dist: tno.mpc.mpyc.stubs>=2.9.0; extra == "schoenfeld-residuals"
Provides-Extra: examples
Requires-Dist: tno.fl.protocols.cox_regression[schoenfeld_residuals]; extra == "examples"
Requires-Dist: statsmodels~=0.14; extra == "examples"
Requires-Dist: matplotlib~=3.0; extra == "examples"
Provides-Extra: tests
Requires-Dist: pytest>=8.1; extra == "tests"
Requires-Dist: pytest-asyncio; extra == "tests"
Requires-Dist: tno.fl.protocols.logistic_regression[tests]; extra == "tests"
Requires-Dist: tno.mpc.communication~=4.8; extra == "tests"
Requires-Dist: tno.fl.protocols.cox_regression[schoenfeld_residuals]; extra == "tests"
Requires-Dist: lifelines>=0.28; extra == "tests"
